vt/utils/errors/error_specs/__constants__.py
vt/utils/errors/error_specs/__init__.py
vt/utils/errors/error_specs/base.py
vt/utils/errors/error_specs/errmsg.py
vt/utils/errors/error_specs/error_codes.py
vt/utils/errors/error_specs/exceptions.py
vt/utils/errors/error_specs/py.typed
vt/utils/errors/error_specs/utils.py
vt/utils/errors/helpers/__init__.py
vt/utils/errors/helpers/argparse_helpers.py
vt/utils/errors/helpers/path_helpers.py
vt/utils/errors/helpers/py.typed
vt/utils/errors/warnings/__init__.py
vt/utils/errors/warnings/py.typed
vt_err_hndlr-0.0.0.dev6.dist-info/licenses/LICENSE
vt_err_hndlr-0.0.0.dev6.dist-info/METADATA
vt_err_hndlr-0.0.0.dev6.dist-info/WHEEL
vt_err_hndlr-0.0.0.dev6.dist-info/top_level.txt
vt_err_hndlr-0.0.0.dev6.dist-info/RECORD
