Metadata-Version: 2.4
Name: vt-err-hndlr
Version: 0.0.0.dev6
Summary: Common errors and warnings for Vaastav Technologies (vt) projects.
Author-email: Suhas Krishna Srivastava <suhas.srivastava@vaastav.tech>
Maintainer-email: Suhas Krishna Srivastava <suhas.srivastava@vaastav.tech>
License-Expression: Apache-2.0
Project-URL: homepage, https://github.com/Vaastav-Technologies/py-err-hndlr
Project-URL: source, https://github.com/Vaastav-Technologies/py-err-hndlr
Project-URL: issues, https://github.com/Vaastav-Technologies/py-eerr-hndlr/issues
Keywords: error,error-handling,error-handler,warning,warn
Classifier: Development Status :: 1 - Planning
Classifier: Intended Audience :: Developers
Classifier: Intended Audience :: Education
Classifier: Topic :: Education
Classifier: Topic :: Software Development :: Libraries
Classifier: Programming Language :: Python :: 3.12
Classifier: Programming Language :: Python :: 3.13
Classifier: Programming Language :: Python :: 3.14
Classifier: Programming Language :: Python :: 3.15
Classifier: Programming Language :: Python :: 3 :: Only
Classifier: Typing :: Typed
Requires-Python: >=3.12
License-File: LICENSE
Requires-Dist: vt-commons>=0.0.1dev9
Dynamic: license-file
